ogls/__init__.py
ogls-1.0.1.dist-info/licenses/LICENSE
ogls-1.0.1.dist-info/WHEEL
ogls-1.0.1.dist-info/METADATA
ogls-1.0.1.dist-info/RECORD
