Metadata-Version: 2.4
Name: ogls
Version: 1.0.1
Summary: Omnivariant generalized least-square regression
Author-email: Mathieu Daëron <daeron@lsce.ipsl.fr>
Requires-Python: >=3.12
Classifier: License :: OSI Approved :: MIT License
License-File: LICENSE
Requires-Dist: numpy >=1.24
Requires-Dist: scipy >=1.10
Requires-Dist: matplotlib >=3.7.1
Requires-Dist: lmfit >=1.2.0
Requires-Dist: loguru >=0.7
Project-URL: Home, https://github.com/mdaeron/ogls
